qsb/__init__.py
qsb/make_site.py
pelican_qsb-0.4.1.dist-info/LICENSE.md
pelican_qsb-0.4.1.dist-info/METADATA
pelican_qsb-0.4.1.dist-info/WHEEL
pelican_qsb-0.4.1.dist-info/entry_points.txt
pelican_qsb-0.4.1.dist-info/top_level.txt
pelican_qsb-0.4.1.dist-info/RECORD
