Metadata-Version: 2.1
Name: pelican-qsb
Version: 0.4.1
Summary: Simple helper for automation Pelican-based site building
Home-page: https://github.com/dmytrohoi/pelican-qsb
Author: Dmytro Hoi
Author-email: dmytro.hoi@gmail.com
License: MIT License
Platform: UNKNOWN
Classifier: Programming Language :: Python :: 3
Classifier: License :: OSI Approved :: MIT License
Classifier: Operating System :: OS Independent
Classifier: Framework :: Pelican
Classifier: Framework :: Pelican :: Plugins
Classifier: Intended Audience :: Developers
Classifier: Topic :: Software Development :: Build Tools
Requires-Python: >=3.6
Requires-Dist: pelican
Requires-Dist: ghp-import
